cpyquickhelper/__init__.py
cpyquickhelper/parallel/threader.cpp
cpyquickhelper/parallel/threader.cpython-37m-darwin.so
cpyquickhelper/parallel/__init__.py
cpyquickhelper/parallel/threader.hpp
cpyquickhelper/parallel/threaderc.cpp
cpyquickhelper/parallel/threadhelper.py
cpyquickhelper/numbers/direct_blas_lapack.cpython-37m-darwin.so
cpyquickhelper/numbers/weighted_number.cpp
cpyquickhelper/numbers/slowcode.cpp
cpyquickhelper/numbers/weighted_number_python.cpp
cpyquickhelper/numbers/cbenchmark_sum_type.h
cpyquickhelper/numbers/cbenchmark_dot.cpp
cpyquickhelper/numbers/cbenchmark_dot.cpython-37m-darwin.so
cpyquickhelper/numbers/cbenchmark_sum_type.cpp
cpyquickhelper/numbers/__init__.py
cpyquickhelper/numbers/speed_measure.py
cpyquickhelper/numbers/cbenchmark.cpp
cpyquickhelper/numbers/repeat_fct.h
cpyquickhelper/numbers/cbenchmark_dot.h
cpyquickhelper/numbers/weighted_dataframe.py
cpyquickhelper/numbers/slowcode.cpython-37m-darwin.so
cpyquickhelper/numbers/cbenchmark_sum_type.cpython-37m-darwin.so
cpyquickhelper/numbers/cbenchmark.cpython-37m-darwin.so
cpyquickhelper/numbers/direct_blas_lapack.pyx
cpyquickhelper/numbers/weighted_number.h
cpyquickhelper/numbers/weighted_number.cpython-37m-darwin.so
cpyquickhelper/io/stdcapture.hpp
cpyquickhelper/io/__init__.py
cpyquickhelper/io/stdchelper.cpython-37m-darwin.so
cpyquickhelper/io/stdhelper.py
cpyquickhelper/io/stdchelper.cpp
cpyquickhelper/io/stdcapture.cpp
cpyquickhelper/algorithms/make_string.hpp
cpyquickhelper/algorithms/__init__.py
cpyquickhelper/algorithms/edit_distance_c.cpp
cpyquickhelper/algorithms/edit_distance.py
cpyquickhelper/algorithms/edit_distance_c.cpython-37m-darwin.so
cpyquickhelper/fastdata/fast_dict_cpy.cpython-37m-darwin.so
cpyquickhelper/fastdata/pandas2numpy.py
cpyquickhelper/fastdata/fast_dict_c.cpython-37m-darwin.so
cpyquickhelper/fastdata/fast_dict.cpython-37m-darwin.so
cpyquickhelper/fastdata/__init__.py
cpyquickhelper/fastdata/fast_dict_cpy.pyx
cpyquickhelper-0.3.412.dist-info/RECORD
cpyquickhelper-0.3.412.dist-info/WHEEL
cpyquickhelper-0.3.412.dist-info/top_level.txt
cpyquickhelper-0.3.412.dist-info/LICENSE.txt
cpyquickhelper-0.3.412.dist-info/METADATA
