Metadata-Version: 2.1
Name: cpyquickhelper
Version: 0.3.412
Summary: Module with C functions. No precise purpose yet.
Home-page: http://www.xavierdupre.fr/app/cpyquickhelper/helpsphinx/index.html
Author: Xavier Dupré
Author-email: xavier.dupre@gmail.com
License: MIT
Download-URL: https://github.com/sdpython/cpyquickhelper/
Keywords: cpyquickhelper,Xavier Dupré
Platform: UNKNOWN
Classifier: Programming Language :: Python :: 3
Classifier: Intended Audience :: Developers
Classifier: Topic :: Scientific/Engineering
Classifier: Topic :: Education
Classifier: License :: OSI Approved :: MIT License
Classifier: Development Status :: 5 - Production/Stable
License-File: LICENSE.txt
Requires-Dist: pybind11
Requires-Dist: numpy (>=1.16)
Requires-Dist: cython
Requires-Dist: scipy
Requires-Dist: pandas (>=1.0)
